[
  {
    "text": "法国没有一个能出球的",
    "length": 10,
    "new_video_time_sec": 82.707
  },
  {
    "text": "这哥们倒霉啊",
    "length": 6,
    "new_video_time_sec": 113.706
  },
  {
    "text": "本人阿根廷球迷，但是想说法国也是真牛逼剩15分钟全场几乎哑火的情况下还能追平",
    "length": 39,
    "new_video_time_sec": 115.294
  },
  {
    "text": "其实从这时候可以看出阿根廷开始有意拖时间了",
    "length": 21,
    "new_video_time_sec": 116.337
  },
  {
    "text": "德保罗被当成球踢",
    "length": 8,
    "new_video_time_sec": 120.478
  },
  {
    "text": "德炮被搞了多少次了",
    "length": 9,
    "new_video_time_sec": 124.968
  },
  {
    "text": "今年西班牙有点强",
    "length": 8,
    "new_video_time_sec": 157.046
  },
  {
    "text": "踢到这里本来以为要结束了，没想到小龟杀出来告诉你什么是卫冕冠军",
    "length": 31,
    "new_video_time_sec": 220.041
  },
  {
    "text": "龟要发力了",
    "length": 5,
    "new_video_time_sec": 236.513
  },
  {
    "text": "奥塔太冲动了",
    "length": 6,
    "new_video_time_sec": 250.525
  },
  {
    "text": "阿根廷传控，达不到西班牙的水平。后卫不行。 还放松下来了。这好被打个突击。",
    "length": 37,
    "new_video_time_sec": 254.534
  },
  {
    "text": "阿根廷后卫还是太拉了",
    "length": 10,
    "new_video_time_sec": 260.943
  },
  {
    "text": "球迷起哄。阿根廷球员也觉得拿下了。就是这一个瞬间，被进了一个。",
    "length": 31,
    "new_video_time_sec": 263.825
  },
  {
    "text": "姆巴佩马上纵逸而歌了",
    "length": 10,
    "new_video_time_sec": 264.376
  },
  {
    "text": "刚才是肯佩斯吗？",
    "length": 8,
    "new_video_time_sec": 267.343
  },
  {
    "text": "奥塔已经卡不住了，不犯规不行了",
    "length": 15,
    "new_video_time_sec": 268.275
  },
  {
    "text": "奥塔门迪拖沓了",
    "length": 7,
    "new_video_time_sec": 268.52
  },
  {
    "text": "裁判真的能左右比赛啊",
    "length": 10,
    "new_video_time_sec": 269.342
  },
  {
    "text": "姆巴佩：各位，属于我的时刻TM来了",
    "length": 17,
    "new_video_time_sec": 279.216
  },
  {
    "text": "迪马利亚：有种不详的预感",
    "length": 12,
    "new_video_time_sec": 282.296
  },
  {
    "text": "当时就记得迪玛利亚一会哭一会笑",
    "length": 15,
    "new_video_time_sec": 284.411
  },
  {
    "text": "因为阿根廷球员的脚下，根本达不到哈维，伊涅斯塔的水平。",
    "length": 27,
    "new_video_time_sec": 284.447
  },
  {
    "text": "法国虽败犹荣，实力其实不输阿根廷",
    "length": 16,
    "new_video_time_sec": 288.475
  },
  {
    "text": "都点球了恩佐还鼓掌",
    "length": 9,
    "new_video_time_sec": 299.874
  },
  {
    "text": "总统都要为我振臂欢呼",
    "length": 10,
    "new_video_time_sec": 302.851
  },
  {
    "text": "法国实力比阿根廷强，但阿根廷更团结而已",
    "length": 19,
    "new_video_time_sec": 312.577
  },
  {
    "text": "龟龟的点球罚的好 有力度 有角度",
    "length": 16,
    "new_video_time_sec": 316.855
  },
  {
    "text": "总统也为我振臂高呼",
    "length": 9,
    "new_video_time_sec": 318.041
  },
  {
    "text": "总统为我欢呼",
    "length": 6,
    "new_video_time_sec": 319.593
  },
  {
    "text": "小马哥真精神",
    "length": 6,
    "new_video_time_sec": 320.523
  },
  {
    "text": "从此，姆巴佩就进入马克龙的法眼了，看看后面美加墨世界杯合影，真是宠死了",
    "length": 36,
    "new_video_time_sec": 332.599
  },
  {
    "text": "马丁判断方向真的强",
    "length": 9,
    "new_video_time_sec": 343.017
  },
  {
    "text": "法国424了",
    "length": 5,
    "new_video_time_sec": 349.184
  },
  {
    "text": "大马丁判断都对了，就是姆巴佩太极限了",
    "length": 18,
    "new_video_time_sec": 352.074
  },
  {
    "text": "换了四个人了吧法国",
    "length": 9,
    "new_video_time_sec": 356.388
  },
  {
    "text": "这回轮到阿根廷人汗流浃背了",
    "length": 13,
    "new_video_time_sec": 370.772
  },
  {
    "text": "哟西很自信啊，结果被断球",
    "length": 12,
    "new_video_time_sec": 392.951
  },
  {
    "text": "金斯利科曼从球王脚下断走了",
    "length": 13,
    "new_video_time_sec": 396.491
  },
  {
    "text": "这球我印象深刻，梅西断球，又被断",
    "length": 16,
    "new_video_time_sec": 396.555
  },
  {
    "text": "叫姆皇！",
    "length": 4,
    "new_video_time_sec": 404.023
  },
  {
    "text": "又是梅西被断球开始导致的丢球",
    "length": 14,
    "new_video_time_sec": 406.741
  },
  {
    "text": "此时的法国人该有多么疯狂",
    "length": 12,
    "new_video_time_sec": 408.295
  },
  {
    "text": "其实看慢放这个马丁内斯碰到了，但是这么快的低平球很难扑",
    "length": 27,
    "new_video_time_sec": 409.512
  },
  {
    "text": "必须尊称一声姆总",
    "length": 8,
    "new_video_time_sec": 414.515
  },
  {
    "text": "神龟",
    "length": 2,
    "new_video_time_sec": 415.849
  },
  {
    "text": "隐身七十分钟 两个点球帽子戏法 这就是球盲最爱吹的",
    "length": 25,
    "new_video_time_sec": 416.19
  },
  {
    "text": "龟龟看什么呢？",
    "length": 7,
    "new_video_time_sec": 416.515
  },
  {
    "text": "回复前面：一定要有一个人留在阿根廷半场，否则阿根廷可以趁法国所有队员都离开阿根廷半场的时间直接开球",
    "length": 49,
    "new_video_time_sec": 426.462
  },
  {
    "text": "阿根廷懵逼了",
    "length": 6,
    "new_video_time_sec": 429.312
  },
  {
    "text": "科曼断梅西那一下很关键",
    "length": 11,
    "new_video_time_sec": 433.128
  },
  {
    "text": "梅西这一笑很有足球漫画里的段子的感觉啊哈哈",
    "length": 22,
    "new_video_time_sec": 434.301
  },
  {
    "text": "老头还笑了",
    "length": 5,
    "new_video_time_sec": 434.512
  },
  {
    "text": "梅西没绷住哈哈哈",
    "length": 8,
    "new_video_time_sec": 435.069
  },
  {
    "text": "科曼到底是怎么追上来的",
    "length": 11,
    "new_video_time_sec": 435.443
  },
  {
    "text": "姆巴佩好在哪？梅西是需要进球，还要负责球队传控节奏，你看看梅西这时候多大了？",
    "length": 38,
    "new_video_time_sec": 436.355
  },
  {
    "text": "当时我看见梅西笑我就知道稳了",
    "length": 14,
    "new_video_time_sec": 436.37
  },
  {
    "text": "出生梅西",
    "length": 4,
    "new_video_time_sec": 436.57
  },
  {
    "text": "当时感觉坏菜了，本来在巴萨就是被逆转",
    "length": 18,
    "new_video_time_sec": 444.374
  },
  {
    "text": "难拿才足以证明世界杯的含金量。才足以值得梅西花十几年去追",
    "length": 28,
    "new_video_time_sec": 444.666
  },
  {
    "text": "我罗碰到这种场面已经尿裤子了",
    "length": 14,
    "new_video_time_sec": 445.983
  },
  {
    "text": "没事科曼丢点",
    "length": 6,
    "new_video_time_sec": 448.729
  },
  {
    "text": "只会看进球的永远不理解老马为什么是球王",
    "length": 20,
    "new_video_time_sec": 457.356
  },
  {
    "text": "金斯利科曼重要抢断",
    "length": 9,
    "new_video_time_sec": 463.301
  },
  {
    "text": "科皇真冷静啊",
    "length": 6,
    "new_video_time_sec": 466.466
  },
  {
    "text": "细节大马丁都碰到球了，埋下点球大战的伏笔",
    "length": 20,
    "new_video_time_sec": 468.971
  },
  {
    "text": "梅西被断球了。王牌失效了。",
    "length": 13,
    "new_video_time_sec": 482.408
  },
  {
    "text": "大马丁扑到了，但是球速太快，手指的力气拦不住。",
    "length": 23,
    "new_video_time_sec": 483.846
  },
  {
    "text": "造就名局的第一功臣姆巴佩",
    "length": 12,
    "new_video_time_sec": 484.098
  },
  {
    "text": "这两球奠定姆巴佩法国球王地位，后面再怎么低迷，有马克龙和德尚撑腰，其他人也得一边去",
    "length": 42,
    "new_video_time_sec": 485.783
  },
  {
    "text": "龟龟这个扫射是真帅",
    "length": 9,
    "new_video_time_sec": 485.983
  },
  {
    "text": "但是，马丁的扑救全是对的",
    "length": 12,
    "new_video_time_sec": 495.915
  },
  {
    "text": "就是这里，老头差点毁了自己的一生",
    "length": 16,
    "new_video_time_sec": 496.016
  },
  {
    "text": "但是阿根廷真的真的很坚韧专注，换其他人这会心态估计都崩了，但是阿根廷全队还是一直咬牙挺到了最后",
    "length": 47,
    "new_video_time_sec": 509.624
  },
  {
    "text": "阿根廷这个冠军含金量十足，真的全队团结坚强拼命下来的，胜不骄败不馁，逆境也没放弃",
    "length": 41,
    "new_video_time_sec": 531.02
  },
  {
    "text": "德保罗：“当被扳平比分时我们整个身体都开始奔溃，梅西站出来鼓舞了我们”",
    "length": 35,
    "new_video_time_sec": 550.24
  },
  {
    "text": "這防守意思是只防突? 覺得姆巴佩肯定想內切打門爭做英雄? 結果直接傳中",
    "length": 35,
    "new_video_time_sec": 573.234
  }
]
